gpt_documenter/__init__.py
gpt_documenter/main.py
gpt_documenter/documenter/__init__.py
gpt_documenter/documenter/documenter.py
gpt_documenter/documenter/templates.py
gpt_documenter/querier/__init__.py
gpt_documenter/querier/querier.py
gpt_documenter/utils/__init__.py
gpt_documenter/utils/utils.py
gptdocumenter-0.1.0.dist-info/LICENCE
gptdocumenter-0.1.0.dist-info/METADATA
gptdocumenter-0.1.0.dist-info/WHEEL
gptdocumenter-0.1.0.dist-info/entry_points.txt
gptdocumenter-0.1.0.dist-info/top_level.txt
gptdocumenter-0.1.0.dist-info/RECORD
