Metadata-Version: 2.1
Name: gptdocumenter
Version: 0.1.0
Summary: Python function documentator using ChatGPT.
Home-page: https://github.com/Caceager/gpt-documenter
Author: Agustín Céspedes
Author-email: agustinces17@gmail.com
License-File: LICENCE
Requires-Dist: langchain (~=0.0.117)
Requires-Dist: openai
Requires-Dist: typer (~=0.7.0)
Requires-Dist: pydantic (~=1.10.6)
Requires-Dist: tiktoken (~=0.3.2)
